graphs_hbruch/__init__.py
graphs_hbruch/heapq.py
graphs_hbruch/sp.py
graphs_hbruch-0.0.1.dist-info/METADATA
graphs_hbruch-0.0.1.dist-info/WHEEL
graphs_hbruch-0.0.1.dist-info/RECORD
